{"cameraMode":{"drawMode":0,"name":"Shaded","section":"Shading Mode"},"sceneLighting":true,"audioPlay":false,"sceneViewState":{"showFog":true,"showMaterialUpdate":false,"showSkybox":true,"showFlares":true,"showImageEffects":true,"showParticleSystems":true},"in2DMode":false,"pivot":{"x":1.5230395793914796,"y":4.537654876708984,"z":1.5468683242797852},"rotation":{"x":-0.14291469752788545,"y":0.11020825058221817,"z":-0.01601533405482769,"w":-0.9834498167037964},"size":8.177166938781739,"orthographic":false}